Funciones_objetivo/__init__.py
Funciones_objetivo/con_restricciones.py
Funciones_objetivo/sin_restricciones.py
Optimizacion_UX21II070-0.1.0.dist-info/LICENSE
Optimizacion_UX21II070-0.1.0.dist-info/METADATA
Optimizacion_UX21II070-0.1.0.dist-info/WHEEL
Optimizacion_UX21II070-0.1.0.dist-info/top_level.txt
Optimizacion_UX21II070-0.1.0.dist-info/RECORD
