Metadata-Version: 2.1
Name: Optimizacion_UX21II070
Version: 0.1.0
Summary: Un paquete de métodos de optimización para funciones univariables y multivariables
Home-page: https://github.com/AngelOr31/Optimizacion_proyecto
Author: Angel Ortega
Author-email: angel-leonz@hotmail.com
Project-URL: Documentation, https://github.com/AngelOr31/Optimizacion_proyecto/docs
Project-URL: Source, https://github.com/AngelOr31/Optimizacion_proyecto
Classifier: Programming Language :: Python :: 3
Classifier: License :: OSI Approved :: MIT License
Classifier: Operating System :: OS Independent
Requires-Python: >=3.10
License-File: LICENSE
Requires-Dist: matplotlib
Requires-Dist: numpy
